{
  "item": "kaleidoscope_fruit_brew:mango_wine",
  "effects": [
    [
      {
        "effect": "minecraft:nausea",
        "duration": 35,
        "amplifier": 0,
        "probability": 1.0
      }
    ],
    [
      {
        "effect": "minecraft:nausea",
        "duration": 10,
        "amplifier": 0,
        "probability": 1.0
      }
    ],
    [
      {
        "effect": "minecraft:strength",
        "duration": 20,
        "amplifier": 2,
        "probability": 1.0
      },
      {
        "effect": "fruitsdelight:rage_aura",
        "duration": 20,
        "amplifier": 0,
        "probability": 1.0
      }
    ],
    [
      {
        "effect": "minecraft:strength",
        "duration": 40,
        "amplifier": 2,
        "probability": 1.0
      },
      {
        "effect": "fruitsdelight:rage_aura",
        "duration": 40,
        "amplifier": 0,
        "probability": 1.0
      }
    ],
    [
      {
        "effect": "minecraft:strength",
        "duration": 80,
        "amplifier": 2,
        "probability": 1.0
      },
      {
        "effect": "fruitsdelight:rage_aura",
        "duration": 80,
        "amplifier": 0,
        "probability": 1.0
      }
    ],
    [
      {
        "effect": "minecraft:strength",
        "duration": 160,
        "amplifier": 2,
        "probability": 1.0
      },
      {
        "effect": "fruitsdelight:rage_aura",
        "duration": 160,
        "amplifier": 0,
        "probability": 1.0
      }
    ],
    [
      {
        "effect": "minecraft:strength",
        "duration": 320,
        "amplifier": 2,
        "probability": 1.0
      },
      {
        "effect": "fruitsdelight:rage_aura",
        "duration": 320,
        "amplifier": 0,
        "probability": 1.0
      }
    ]
  ]
}